vcdriver/__init__.py
vcdriver/config.py
vcdriver/exceptions.py
vcdriver/folder.py
vcdriver/helpers.py
vcdriver/session.py
vcdriver/vm.py
vcdriver2-0.0.1.dist-info/LICENSE
vcdriver2-0.0.1.dist-info/METADATA
vcdriver2-0.0.1.dist-info/WHEEL
vcdriver2-0.0.1.dist-info/top_level.txt
vcdriver2-0.0.1.dist-info/RECORD
