Metadata-Version: 2.1
Name: vcdriver2
Version: 0.0.1
Summary: A vcenter driver based on pyvmomi, fabric and pywinrm
Home-page: https://github.com/Osirium/vcdriver
Author: UNKNOWN
Author-email: UNKNOWN
License: MIT
Platform: UNKNOWN
Classifier: Development Status :: 5 - Production/Stable
Classifier: Intended Audience :: Developers
Classifier: Intended Audience :: System Administrators
Classifier: License :: OSI Approved :: MIT License
Classifier: Operating System :: OS Independent
Classifier: Programming Language :: Python
Classifier: Programming Language :: Python :: 2
Classifier: Programming Language :: Python :: 2.7
Classifier: Programming Language :: Python :: 3
Classifier: Programming Language :: Python :: 3.4
Classifier: Programming Language :: Python :: 3.5
Classifier: Programming Language :: Python :: 3.6
Classifier: Topic :: Software Development
Requires-Dist: colorama
Requires-Dist: Fabric3
Requires-Dist: pyvmomi
Requires-Dist: pywinrm2
Requires-Dist: six
